chunk_it_pro/__init__.py
chunk_it_pro/config.py
chunk_it_pro/pipeline.py
chunk_it_pro/chunkers/__init__.py
chunk_it_pro/chunkers/initial_chunker.py
chunk_it_pro/chunkers/semantic_chunker.py
chunk_it_pro/embeddings/__init__.py
chunk_it_pro/embeddings/embedding_analyzer.py
chunk_it_pro/embeddings/voyage_client.py
chunk_it_pro/parsers/__init__.py
chunk_it_pro/parsers/document_parser.py
chunk_it_pro/parsers/omniparse.py
chunk_it_pro/utils/__init__.py
chunk_it_pro/utils/singleton.py
chunk_it_pro-0.1.4.dist-info/METADATA
chunk_it_pro-0.1.4.dist-info/WHEEL
chunk_it_pro-0.1.4.dist-info/top_level.txt
chunk_it_pro-0.1.4.dist-info/RECORD
