Metadata-Version: 2.4
Name: chunk-it-pro
Version: 0.1.4
Summary: A semantic document chunking library
Home-page: https://github.com/adw777/chunk-it-pro
Author: ChunkIt Pro Contributors
Author-email: ChunkIt Pro Contributors <aman.dogra@thewasserstoff.com>
License: MIT
Project-URL: Homepage, https://github.com/adw777/chunk-it-pro
Project-URL: Bug Reports, https://github.com/adw777/chunk-it-pro/issues
Project-URL: Source, https://github.com/adw777/chunk-it-pro
Project-URL: Documentation, https://chunk-it-pro.readthedocs.io/
Classifier: Development Status :: 4 - Beta
Classifier: Intended Audience :: Developers
Classifier: License :: OSI Approved :: MIT License
Classifier: Operating System :: OS Independent
Classifier: Programming Language :: Python :: 3
Classifier: Programming Language :: Python :: 3.8
Classifier: Programming Language :: Python :: 3.9
Classifier: Programming Language :: Python :: 3.10
Classifier: Programming Language :: Python :: 3.11
Requires-Python: >=3.9
Requires-Dist: numpy>=1.21.0
Requires-Dist: matplotlib>=3.5.0
Requires-Dist: scikit-learn>=1.0.0
Requires-Dist: nltk>=3.7
Requires-Dist: tiktoken>=0.3.0
Requires-Dist: scipy>=1.7.0
Requires-Dist: pathlib2>=2.3.0
Requires-Dist: python-dotenv>=0.19.0
Requires-Dist: PyMuPDF>=1.20.0
Requires-Dist: python-docx>=0.8.11
Requires-Dist: mammoth>=1.5.0
Requires-Dist: openai>=1.0.0
Requires-Dist: voyageai>=0.2.0
Requires-Dist: sentence-transformers>=2.2.0
Requires-Dist: requests>=2.28.0
Provides-Extra: dev
Requires-Dist: pytest>=6.0; extra == "dev"
Requires-Dist: pytest-asyncio>=0.18.0; extra == "dev"
Requires-Dist: black>=22.0.0; extra == "dev"
Requires-Dist: flake8>=4.0.0; extra == "dev"
Requires-Dist: mypy>=0.950; extra == "dev"
Provides-Extra: docs
Requires-Dist: sphinx>=4.0.0; extra == "docs"
Requires-Dist: sphinx-rtd-theme>=1.0.0; extra == "docs"
Dynamic: author
Dynamic: home-page
Dynamic: requires-python
